tge_spect/piso.v
module piso #(
    parameter INPUT_SIZE = 256,
    parameter OUTPUT_SIZE = 64
)
(
    input wire clk,
    input wire ce,
    input wire rst,

    input wire [INPUT_SIZE-1:0] i_parallel,
    output wire [OUTPUT_SIZE-1:0] o_serial,
    
    input wire      fifo_empty,
    output wire     fifo_re,

    output wire     valid
);

// module that interface a fifo that contains parallel data
//that we wish to serialize.
//note that for each value that we read from the fifo we need 
// INPUT_SIZE/OUTPUT_SIZE cycles until we could read the next val

parameter CYCLES_BTW = INPUT_SIZE/OUTPUT_SIZE; 

parameter IDLE = 2'b0;
parameter BUSY = 2'b1;



reg [$clog2(CYCLES_BTW)-1:0] counter=0;
reg re, valid_r; //read enable and valid..

reg state=IDLE, next_state=IDLE;


always@(posedge clk)begin
    if(rst)
        state <= IDLE;
    else
        state <= next_state;
end


always@(*)begin
    case(state)
        IDLE:   begin
            if(~fifo_empty)     next_state = BUSY;
            else                next_state = IDLE;
        end
        BUSY:   begin
            if(counter==(CYCLES_BTW)-1) next_state = IDLE;
            else                        next_state = BUSY;
        end
    endcase 
end

always@(posedge clk)begin
    case(state)
        IDLE: begin
            counter<=0;
            valid_r <= 0;
        end
        BUSY: begin
            valid_r<= 1;
            counter <= counter +1;
        end
    endcase
end


always@(posedge clk)begin
    re = ~state && next_state && ~rst;
end

//detect the transition of states
assign fifo_re = re; 


reg [OUTPUT_SIZE-1:0] serial_out;


always@(*)begin
    case(counter)
        1: serial_out = i_parallel[OUTPUT_SIZE-1:0];
        2: serial_out = i_parallel[2*OUTPUT_SIZE-1:1*OUTPUT_SIZE];
        3: serial_out = i_parallel[3*OUTPUT_SIZE-1:2*OUTPUT_SIZE];
        0: serial_out = i_parallel[4*OUTPUT_SIZE-1:3*OUTPUT_SIZE];
    endcase
end


/*
always@(*)begin
    integer i;
    for(i=0; i<CYCLES_BTW;i=i+1)begin: loop
        if(counter==i)begin
            serial_out = i_parallel[(i+1)*OUTPUT_SIZE-1:i*OUTPUT_SIZE];
        end
    end
end
*/

assign valid = valid_r;
assign o_serial = serial_out; 
endmodule

tge_spect/piso_tb.v
module piso_tb;
    parameter INPUT_SIZE = 256;
    parameter OUTPUT_SIZE = 64;


    reg  clk;
    reg  ce;
    reg  rst;

    reg  [INPUT_SIZE-1:0] i_parallel;
    wire  [OUTPUT_SIZE-1:0] o_serial;
    
    reg       fifo_empty;
    wire      fifo_re;

    wire      valid;


piso #( 
    .INPUT_SIZE(INPUT_SIZE),
    .OUTPUT_SIZE(OUTPUT_SIZE)
) piso (
    .clk(clk),
    .ce(ce),
    .rst(rst),
    .i_parallel(i_parallel),
    .o_serial(o_serial),
    .fifo_empty(fifo_empty),
    .fifo_re(fifo_re),
    .valid(valid)
);


initial begin
    clk = 0;
    ce = 1;
    rst = 0;
    i_parallel = {{64'd0, 64'd1}, {64'd2, 64'd3}};
    fifo_empty = 1;
end


parameter HALF_PERIOD =  5;
parameter PERIOD = 10;

always
    #HALF_PERIOD clk = ~clk;


initial begin
    $dumpfile("piso.vcd");
    $dumpvars();
end

initial begin
    rst = 1;
    #(3*PERIOD);
    rst = 0;
    #(10*PERIOD);
    fifo_empty = 0;
    #(30*PERIOD);
    $finish;
end


endmodule

tge_spect/piso.vcd
$date
	Tue Sep  8 23:09:45 2020
$end
$version
	Icarus Verilog
$end
$timescale
	1s
$end
$scope module piso_tb $end
$var wire 1 ! valid $end
$var wire 64 " o_serial [63:0] $end
$var wire 1 # fifo_re $end
$var reg 1 $ ce $end
$var reg 1 % clk $end
$var reg 1 & fifo_empty $end
$var reg 256 ' i_parallel [255:0] $end
$var reg 1 ( rst $end
$scope module piso $end
$var wire 1 $ ce $end
$var wire 1 % clk $end
$var wire 1 & fifo_empty $end
$var wire 1 # fifo_re $end
$var wire 256 ) i_parallel [255:0] $end
$var wire 64 * o_serial [63:0] $end
$var wire 1 ( rst $end
$var wire 1 ! valid $end
$var reg 2 + counter [1:0] $end
$var reg 1 , next_state $end
$var reg 1 - re $end
$var reg 64 . serial_out [63:0] $end
$var reg 1 / state $end
$var reg 1 0 valid_r $end
$upscope $end
$upscope $end
$enddefinitions $end
#0
$dumpvars
x0
0/
b0 .
x-
0,
b0 +
b0 *
b100000000000000000000000000000000000000000000000000000000000000100000000000000000000000000000000000000000000000000000000000000011 )
1(
b100000000000000000000000000000000000000000000000000000000000000100000000000000000000000000000000000000000000000000000000000000011 '
1&
0%
1$
x#
b0 "
x!
$end
#5
0!
00
0#
0-
1%
#10
0%
#15
1%
#20
0%
#25
1%
#30
0%
0(
#35
1%
#40
0%
#45
1%
#50
0%
#55
1%
#60
0%
#65
1%
#70
0%
#75
1%
#80
0%
#85
1%
#90
0%
#95
1%
#100
0%
#105
1%
#110
0%
#115
1%
#120
0%
#125
1%
#130
1,
0%
0&
#135
1/
1#
1-
1%
#140
0%
#145
b11 "
b11 *
b11 .
b1 +
1!
10
0#
0-
1%
#150
0%
#155
b10 "
b10 *
b10 .
b10 +
1%
#160
0%
#165
b1 "
b1 *
b1 .
0,
b11 +
1%
#170
0%
#175
b0 "
b0 *
b0 .
1,
b0 +
0/
1%
#180
0%
#185
1/
0!
00
1#
1-
1%
#190
0%
#195
b11 "
b11 *
b11 .
b1 +
1!
10
0#
0-
1%
#200
0%
#205
b10 "
b10 *
b10 .
b10 +
1%
#210
0%
#215
b1 "
b1 *
b1 .
0,
b11 +
1%
#220
0%
#225
b0 "
b0 *
b0 .
1,
0/
b0 +
1%
#230
0%
#235
0!
00
1/
1#
1-
1%
#240
0%
#245
b11 "
b11 *
b11 .
b1 +
1!
10
0#
0-
1%
#250
0%
#255
b10 "
b10 *
b10 .
b10 +
1%
#260
0%
#265
b1 "
b1 *
b1 .
0,
b11 +
1%
#270
0%
#275
b0 "
b0 *
b0 .
1,
b0 +
0/
1%
#280
0%
#285
1/
0!
00
1#
1-
1%
#290
0%
#295
b11 "
b11 *
b11 .
b1 +
1!
10
0#
0-
1%
#300
0%
#305
b10 "
b10 *
b10 .
b10 +
1%
#310
0%
#315
b1 "
b1 *
b1 .
0,
b11 +
1%
#320
0%
#325
b0 "
b0 *
b0 .
1,
0/
b0 +
1%
#330
0%
#335
0!
00
1/
1#
1-
1%
#340
0%
#345
b11 "
b11 *
b11 .
b1 +
1!
10
0#
0-
1%
#350
0%
#355
b10 "
b10 *
b10 .
b10 +
1%
#360
0%
#365
b1 "
b1 *
b1 .
0,
b11 +
1%
#370
0%
#375
b0 "
b0 *
b0 .
1,
b0 +
0/
1%
#380
0%
#385
1/
0!
00
1#
1-
1%
#390
0%
#395
b11 "
b11 *
b11 .
b1 +
1!
10
0#
0-
1%
#400
0%
#405
b10 "
b10 *
b10 .
b10 +
1%
#410
0%
#415
b1 "
b1 *
b1 .
0,
b11 +
1%
#420
0%
#425
b0 "
b0 *
b0 .
1,
0/
b0 +
1%
